{
  "name": "CodeTest",
  "tree": {
    "$className": "DataModel",

    "ReplicatedStorage": {
      "$ignoreUnknownInstances": true,
      "$className": "ReplicatedStorage",
      "$path": "src/ReplicatedStorage"
    },

    "ServerScriptService": {
      "$ignoreUnknownInstances": true,
      "$className": "ServerScriptService",
      "$path": "src/ServerScriptService"
    },

    "StarterPlayer": {
      "$className": "StarterPlayer",
      "$ignoreUnknownInstances": true,
      "StarterPlayerScripts": {
        "$ignoreUnknownInstances": true,
        "$className": "StarterPlayerScripts",
        "$path": "src/StarterPlayer"
      }
    }
  }
}